rust_mahjong-0.1.0.dist-info/METADATA
rust_mahjong-0.1.0.dist-info/WHEEL
rust_mahjong-0.1.0.dist-info/licenses/LICENSE
mahjong.libs/libgcc_s-b5472b99.so.1
mahjong/__init__.py
mahjong/mahjong.pypy39-pp73-x86-linux-gnu.so
rust_mahjong-0.1.0.dist-info/RECORD
